keyvaultlib/__init__.py
keyvaultlib/key_vault.py
keyvaultlib-1.1.4.dist-info/LICENSE
keyvaultlib-1.1.4.dist-info/METADATA
keyvaultlib-1.1.4.dist-info/WHEEL
keyvaultlib-1.1.4.dist-info/top_level.txt
keyvaultlib-1.1.4.dist-info/RECORD
