Metadata-Version: 2.1
Name: keyvaultlib
Version: 1.1.4
Summary: A KeyVault client wrapper that helps transition between using ADAL (Active Directory Authentication Libraries) and MSI (Managed Service Identity) as a token provider
Home-page: https://github.com/dany74q/keyvaultlib
Author: Danny Shemesh
Author-email: dany74q@gmail.com
License: UNKNOWN
Keywords: keyvault azure adal msi managed-service-identity
Platform: UNKNOWN
Classifier: Development Status :: 5 - Production/Stable
Classifier: Intended Audience :: Developers
Classifier: Topic :: Software Development :: Libraries :: Python Modules
Classifier: License :: OSI Approved :: MIT License
Classifier: Programming Language :: Python :: 2
Classifier: Programming Language :: Python :: 2.7
Classifier: Programming Language :: Python :: 3
Classifier: Programming Language :: Python :: 3.4
Classifier: Programming Language :: Python :: 3.5
Classifier: Programming Language :: Python :: 3.6
Requires-Dist: msrestazure (==0.5.0)
Requires-Dist: azure-keyvault (==1.1.0)
Requires-Dist: azure-common (==1.1.16)
Requires-Dist: six (>=1.12.0)
Requires-Dist: urllib3 (==1.24.3)
